udemy_dl/__init__.py
udemy_dl/__main__.py
udemy_dl/argparser.py
udemy_dl/cli.py
udemy_dl/course.py
udemy_dl/downloader.py
udemy_dl/exceptions.py
udemy_dl/session.py
udemy_dl/udemy_download.py
udemy_dl/utils.py
udemydl-0.6.1.dist-info/LICENSE
udemydl-0.6.1.dist-info/METADATA
udemydl-0.6.1.dist-info/WHEEL
udemydl-0.6.1.dist-info/entry_points.txt
udemydl-0.6.1.dist-info/top_level.txt
udemydl-0.6.1.dist-info/RECORD
