Metadata-Version: 2.1
Name: udemydl
Version: 0.6.1
Summary: Download videos from Udemy for personal offline use
Home-page: https://github.com/lestex/udemydl
Author: Andrey Larin
Author-email: lestex@gmail.com
License: UNKNOWN
Platform: UNKNOWN
Classifier: Environment :: Console
Classifier: Programming Language :: Python :: 2
Classifier: Programming Language :: Python :: 3
Classifier: Topic :: Multimedia :: Video
Requires-Dist: requests
Requires-Dist: distro
Requires-Dist: cloudscraper
